Workbook

Sheet Summary
A1: Devometrics pricing model
A2: Feature-based pricing built bottom-up from measured AI cost, to land a 75-80% gross margin. Every number below is a formula; change Inputs and it recalculates.
A4: AI cost per seat per month | B4: Light | C4: Typical | D4: Heavy | E4: Reading
A5: English | B5: =Usage!J35 -> 0.11813493 | C5: =Usage!K35 -> 0.4150958 | D5: =Usage!L35 -> 1.3018475 | E5: Even heavy English use costs about a dollar per seat.
A6: Arabic | B6: =Usage!M35 -> 0.24572065 | C6: =Usage!N35 -> 0.83503126 | D6: =Usage!O35 -> 2.4691629 | E6: Arabic roughly doubles token costs (measured 2.08x).
A7: Blended (Arabic share on Inputs) | B7: =Usage!J36 -> 0.18192779 | C7: =Usage!K36 -> 0.62506353 | D7: =Usage!L36 -> 1.8855052
A9: Gross margin at the Complete price | B9: Light | C9: Typical | D9: Heavy | E9: Reading
A10: Complete price per seat per month | B10: =Inputs!B43 -> 8
A11: Platform size used (paying seats) | B11: =Pricing!B4 -> 250
A12: Gross margin | B12: =Pricing!B14 -> 0.81700903 | C12: =Pricing!C14 -> 0.76161706 | D12: =Pricing!D14 -> 0.60406185 | E12: Compare with the 75-80% target on Inputs.
A14: Platform size needed to reach the target (Typical usage) | B14: Low target | C14: High target | E14: Reading
A15: Paying seats on the platform | B15: =IF(Inputs!$B$43*(1-Inputs!$B$33-Inputs!$B$34-Inputs!$B$37)-Usage!$K$36-Inputs!$B$32<=0,"not reachable",ROUNDUP(Inputs!$B$29/(Inputs!$B$43*(1-Inputs!$B$33-Inputs!$B$34-Inputs!$B$37)-Usage!$K$36-Inputs!$B$32),0)) -> 206 | C15: =IF(Inputs!$B$43*(1-Inputs!$B$33-Inputs!$B$34-Inputs!$B$38)-Usage!$K$36-Inputs!$B$32<=0,"not reachable",ROUNDUP(Inputs!$B$29/(Inputs!$B$43*(1-Inputs!$B$33-Inputs!$B$34-Inputs!$B$38)-Usage!$K$36-Inputs!$B$32),0)) -> 865 | E15: Below this size the fixed platform cost drags margin under target; use a minimum monthly fee per client until you pass it.
A17: Fixed platform cost | B17: Value | E17: Reading
A18: Total fixed per month | B18: =Inputs!B29 -> 108
A19: Minimum monthly fee per client to cover its share at 5 clients | B19: =Inputs!B29/5/(1-Inputs!B33-Inputs!B34) -> 24 | E19: Rough guide for a per-client minimum, e.g. a 10-seat floor.
A21: Saving from three small product changes (Typical, English) | B21: Per seat/mo | E21: Reading
A22: Daily insight on Haiku, Coach memory every 5th message, cache course recommendations | B22: =Guardrails!B20 -> 0.12384736
A23: Typical gross margin after those changes (same price and size) | B23: =Guardrails!B23 -> 0.78545768
A26: Legend
A27: Blue text = input you can change. Yellow fill = key assumption to confirm. Green text = pulled from another sheet. Black = formula.
A28: Sheets: Inputs (all assumptions) > AI_Costs (cost per use) > Usage (cost per seat) > Pricing (margins) > Guardrails (caps and savings) > Features (what is free).
A29: Prices on Inputs are a starting recommendation. There is no market-rate benchmarking in this model; compare to your existing $9 / $7.50 / $6 grid.

Sheet Inputs
A1: Inputs and assumptions
A2: Blue = an input you can change. Yellow = a key assumption to confirm. Every other sheet is formulas off this one.
A3: Model rates ($ per 1M tokens) | B3: Input | C3: Output | D3: Source / note
A4: sonnet | B4: 3 | C4: 15 | D4: claude-sonnet-5 list rate (lib/aiUsage/track.ts). The introductory $2/$10 ended 31 Aug 2026.
A5: haiku | B5: 1 | C5: 5 | D5: claude-haiku-4-5 list rate (Coach, Roleplay, Coach memory).
A6: mini | B6: 0.75 | C6: 4.5 | D6: openai/gpt-5.4-mini via OpenRouter (drafting features).
A8: Speech (Microsoft Azure) | B8: Value | D8: Source / note
A9: Speech-to-text, $ per audio hour | B9: 1 | D9: Azure Speech standard real-time rate. VERIFY against your Azure bill.
A10: Text-to-speech (neural), $ per 1M characters | B10: 16 | D10: Azure neural TTS list rate. VERIFY against your Azure bill.
A11: Voice role-play session: minutes of speech | B11: 10 | D11: Assumption: a typical spoken practice session.
A12: Voice role-play session: characters spoken back | B12: 6000 | D12: Assumption: ~10 replies of ~600 characters.
A13: Coach voice exchange: minutes of speech | B13: 0.5 | D13: Assumption.
A14: Coach voice exchange: characters spoken back | B14: 600 | D14: Assumption.
A16: Language | B16: Value | D16: Source / note
A17: Arabic token multiplier (token cost only) | B17: 2.08 | D17: Measured 2.08x on the same Coach exchange in Arabic vs English (your 30 Jul routing analysis).
A18: Share of usage that is in Arabic | B18: 0.5 | D18: ASSUMPTION for a MENA-focused client base. Set to your real mix once Sentry/usage data exists.
A20: Fixed platform costs ($ per month) | B20: Value | D20: Source / note
A21: Supabase Pro | B21: 25 | D21: Database, auth, storage. Includes daily backups (7 days).
A22: Supabase compute upgrade (Small) | B22: 15 | D22: Headroom for a few hundred active users. VERIFY current price.
A23: Vercel Pro (1 seat) | B23: 20 | D23: Hosting.
A24: Sentry Team | B24: 26 | D24: Error monitoring. VERIFY current price.
A25: Resend Pro | B25: 20 | D25: Transactional email (50k/month).
A26: Domain, DNS, misc. | B26: 2 | D26: Assumption.
A27: Point-in-time recovery add-on | B27: 100 | D27: Optional Supabase add-on. Set the switch below to 1 to include.
A28: Include point-in-time recovery? (1 = yes, 0 = no) | B28: 0
A29: Total fixed platform cost ($/month) | B29: =SUM(B21:B26)+B27*B28 -> 108
A31: Variable costs and revenue-linked costs | B31: Value | D31: Source / note
A32: Storage, bandwidth and email per seat ($/month) | B32: 0.05 | D32: Assumption: documents, SCORM, CVs, reminders. Re-measure after the pilot.
A33: Support and customer success (% of revenue) | B33: 0.08 | D33: ASSUMPTION. Counted as cost of revenue so the margin is conservative.
A34: Payment processing (% of revenue) | B34: 0.02 | D34: Blended bank transfer / card fees. Lemon Squeezy card payments are higher (5% + $0.50).
A36: Margin target | B36: Value | D36: Note
A37: Target gross margin: low end | B37: 0.75 | D37: Gross margin here = revenue minus AI, hosting, storage, support and payment costs.
A38: Target gross margin: high end | B38: 0.8
A40: Feature-based prices ($ per employee per month) | B40: Value | D40: Note
A41: Core HR (all free-to-run modules) | B41: 3.5 | D41: Starting recommendation. Compare to your existing grid ($9 / $7.50 / $6). Change freely.
A42: Talent Intelligence (AI modules) | B42: 4.5
A43: Complete (Core HR + Talent Intelligence) | B43: =B41+B42 -> 8

Sheet AI_Costs
A1: AI cost per use, by feature
A2: Models and token caps come from the real call sites. Token counts are estimates sized to each feature's content and cross-checked against recorded events (Coach $0.0027, succession ranking $0.0166, web-search course recommendations $0.089).
A4: ID | B4: Feature | C4: Triggered by | D4: Model | E4: Input tokens | F4: Output tokens | G4: Voice minutes | H4: TTS characters | I4: Token cost (EN) | J4: Voice cost | K4: Total per use (EN) | L4: Total per use (AR) | M4: Cost class | N4: Note
A5: A1 | B5: Daily insight | C5: Dashboard load, once per user per day | D5: sonnet | E5: 1800 | F5: 120 | G5: 0 | H5: 0 | I5: =IFERROR((E5*INDEX(Inputs!$B$4:$B$6,MATCH(D5,Inputs!$A$4:$A$6,0))+F5*INDEX(Inputs!$C$4:$C$6,MATCH(D5,Inputs!$A$4:$A$6,0)))/1000000,0) -> 0.0072 | J5: =G5/60*Inputs!$B$9+H5/1000000*Inputs!$B$10 -> 0 | K5: =I5+J5 -> 0.0072 | L5: =I5*Inputs!$B$17+J5 -> 0.014976 | M5: D | N5: Runs for EVERY active user whether or not they use AI. Biggest baseline cost; a Haiku call would be ~3x cheaper.
A6: A2 | B6: Coach reply | C6: Each Coach message | D6: haiku | E6: 1300 | F6: 280 | G6: 0 | H6: 0 | I6: =IFERROR((E6*INDEX(Inputs!$B$4:$B$6,MATCH(D6,Inputs!$A$4:$A$6,0))+F6*INDEX(Inputs!$C$4:$C$6,MATCH(D6,Inputs!$A$4:$A$6,0)))/1000000,0) -> 0.0027 | J6: =G6/60*Inputs!$B$9+H6/1000000*Inputs!$B$10 -> 0 | K6: =I6+J6 -> 0.0027 | L6: =I6*Inputs!$B$17+J6 -> 0.005616 | M6: C | N6: Measured: ~1,288 in / 281 out.
A7: A3 | B7: Coach memory update | C7: After every Coach message | D7: haiku | E7: 1400 | F7: 250 | G7: 0 | H7: 0 | I7: =IFERROR((E7*INDEX(Inputs!$B$4:$B$6,MATCH(D7,Inputs!$A$4:$A$6,0))+F7*INDEX(Inputs!$C$4:$C$6,MATCH(D7,Inputs!$A$4:$A$6,0)))/1000000,0) -> 0.00265 | J7: =G7/60*Inputs!$B$9+H7/1000000*Inputs!$B$10 -> 0 | K7: =I7+J7 -> 0.00265 | L7: =I7*Inputs!$B$17+J7 -> 0.005512 | M7: C | N7: Measured. Doubles the cost of each Coach exchange.
A8: A4 | B8: Coach session summary | C8: Per Coach session (~8 messages) | D8: haiku | E8: 3500 | F8: 700 | G8: 0 | H8: 0 | I8: =IFERROR((E8*INDEX(Inputs!$B$4:$B$6,MATCH(D8,Inputs!$A$4:$A$6,0))+F8*INDEX(Inputs!$C$4:$C$6,MATCH(D8,Inputs!$A$4:$A$6,0)))/1000000,0) -> 0.007 | J8: =G8/60*Inputs!$B$9+H8/1000000*Inputs!$B$10 -> 0 | K8: =I8+J8 -> 0.007 | L8: =I8*Inputs!$B$17+J8 -> 0.01456 | M8: C | N8: Estimate.
A9: A5 | B9: Role-play turn (text) | C9: Each role-play turn | D9: haiku | E9: 1800 | F9: 300 | G9: 0 | H9: 0 | I9: =IFERROR((E9*INDEX(Inputs!$B$4:$B$6,MATCH(D9,Inputs!$A$4:$A$6,0))+F9*INDEX(Inputs!$C$4:$C$6,MATCH(D9,Inputs!$A$4:$A$6,0)))/1000000,0) -> 0.0033 | J9: =G9/60*Inputs!$B$9+H9/1000000*Inputs!$B$10 -> 0 | K9: =I9+J9 -> 0.0033 | L9: =I9*Inputs!$B$17+J9 -> 0.006864 | M9: C | N9: A session is ~10 turns.
A10: A6 | B10: Voice role-play session (speech only) | C10: Per voice session | D10: voice | E10: 0 | F10: 0 | G10: =Inputs!$B$11 -> 10 | H10: =Inputs!$B$12 -> 6000 | I10: =IFERROR((E10*INDEX(Inputs!$B$4:$B$6,MATCH(D10,Inputs!$A$4:$A$6,0))+F10*INDEX(Inputs!$C$4:$C$6,MATCH(D10,Inputs!$A$4:$A$6,0)))/1000000,0) -> 0 | J10: =G10/60*Inputs!$B$9+H10/1000000*Inputs!$B$10 -> 0.26266667 | K10: =I10+J10 -> 0.26266667 | L10: =I10*Inputs!$B$17+J10 -> 0.26266667 | M10: E | N10: Azure speech-to-text + text-to-speech for one session. Add the text turns separately.
A11: A7 | B11: Coach voice exchange (speech only) | C11: Per spoken Coach exchange | D11: voice | E11: 0 | F11: 0 | G11: =Inputs!$B$13 -> 0.5 | H11: =Inputs!$B$14 -> 600 | I11: =IFERROR((E11*INDEX(Inputs!$B$4:$B$6,MATCH(D11,Inputs!$A$4:$A$6,0))+F11*INDEX(Inputs!$C$4:$C$6,MATCH(D11,Inputs!$A$4:$A$6,0)))/1000000,0) -> 0 | J11: =G11/60*Inputs!$B$9+H11/1000000*Inputs!$B$10 -> 0.017933333 | K11: =I11+J11 -> 0.017933333 | L11: =I11*Inputs!$B$17+J11 -> 0.017933333 | M11: E | N11: Azure speech only.
A12: A8 | B12: Gap analysis: competency extraction | C12: Each gap analysis | D12: sonnet | E12: 7000 | F12: 2500 | G12: 0 | H12: 0 | I12: =IFERROR((E12*INDEX(Inputs!$B$4:$B$6,MATCH(D12,Inputs!$A$4:$A$6,0))+F12*INDEX(Inputs!$C$4:$C$6,MATCH(D12,Inputs!$A$4:$A$6,0)))/1000000,0) -> 0.0585 | J12: =G12/60*Inputs!$B$9+H12/1000000*Inputs!$B$10 -> 0 | K12: =I12+J12 -> 0.0585 | L12: =I12*Inputs!$B$17+J12 -> 0.12168 | M12: D | N12: CV + job description + prompt. Largest single employee-run call.
A13: A9 | B13: Gap analysis: role-context inference | C13: Each gap analysis | D13: sonnet | E13: 2500 | F13: 700 | G13: 0 | H13: 0 | I13: =IFERROR((E13*INDEX(Inputs!$B$4:$B$6,MATCH(D13,Inputs!$A$4:$A$6,0))+F13*INDEX(Inputs!$C$4:$C$6,MATCH(D13,Inputs!$A$4:$A$6,0)))/1000000,0) -> 0.018 | J13: =G13/60*Inputs!$B$9+H13/1000000*Inputs!$B$10 -> 0 | K13: =I13+J13 -> 0.018 | L13: =I13*Inputs!$B$17+J13 -> 0.03744 | M13: D | N13: Runs with each analysis.
A14: A10 | B14: Resume Intelligence | C14: Each CV audit | D14: sonnet | E14: 6000 | F14: 2500 | G14: 0 | H14: 0 | I14: =IFERROR((E14*INDEX(Inputs!$B$4:$B$6,MATCH(D14,Inputs!$A$4:$A$6,0))+F14*INDEX(Inputs!$C$4:$C$6,MATCH(D14,Inputs!$A$4:$A$6,0)))/1000000,0) -> 0.0555 | J14: =G14/60*Inputs!$B$9+H14/1000000*Inputs!$B$10 -> 0 | K14: =I14+J14 -> 0.0555 | L14: =I14*Inputs!$B$17+J14 -> 0.11544 | M14: D
A15: A11 | B15: Career GPS what-if | C15: Each what-if | D15: sonnet | E15: 2500 | F15: 500 | G15: 0 | H15: 0 | I15: =IFERROR((E15*INDEX(Inputs!$B$4:$B$6,MATCH(D15,Inputs!$A$4:$A$6,0))+F15*INDEX(Inputs!$C$4:$C$6,MATCH(D15,Inputs!$A$4:$A$6,0)))/1000000,0) -> 0.015 | J15: =G15/60*Inputs!$B$9+H15/1000000*Inputs!$B$10 -> 0 | K15: =I15+J15 -> 0.015 | L15: =I15*Inputs!$B$17+J15 -> 0.0312 | M15: D
A16: A12 | B16: Notes analysis | C16: Each analysed note | D16: sonnet | E16: 1500 | F16: 600 | G16: 0 | H16: 0 | I16: =IFERROR((E16*INDEX(Inputs!$B$4:$B$6,MATCH(D16,Inputs!$A$4:$A$6,0))+F16*INDEX(Inputs!$C$4:$C$6,MATCH(D16,Inputs!$A$4:$A$6,0)))/1000000,0) -> 0.0135 | J16: =G16/60*Inputs!$B$9+H16/1000000*Inputs!$B$10 -> 0 | K16: =I16+J16 -> 0.0135 | L16: =I16*Inputs!$B$17+J16 -> 0.02808 | M16: D
A17: A13 | B17: Case-study scoring | C17: Each scored exercise | D17: sonnet | E17: 2000 | F17: 700 | G17: 0 | H17: 0 | I17: =IFERROR((E17*INDEX(Inputs!$B$4:$B$6,MATCH(D17,Inputs!$A$4:$A$6,0))+F17*INDEX(Inputs!$C$4:$C$6,MATCH(D17,Inputs!$A$4:$A$6,0)))/1000000,0) -> 0.0165 | J17: =G17/60*Inputs!$B$9+H17/1000000*Inputs!$B$10 -> 0 | K17: =I17+J17 -> 0.0165 | L17: =I17*Inputs!$B$17+J17 -> 0.03432 | M17: D
A18: A14 | B18: Course recommendations (web search) | C18: Each recommendation request | D18: sonnet | E18: 21452 | F18: 1646 | G18: 0 | H18: 0 | I18: =IFERROR((E18*INDEX(Inputs!$B$4:$B$6,MATCH(D18,Inputs!$A$4:$A$6,0))+F18*INDEX(Inputs!$C$4:$C$6,MATCH(D18,Inputs!$A$4:$A$6,0)))/1000000,0) -> 0.089046 | J18: =G18/60*Inputs!$B$9+H18/1000000*Inputs!$B$10 -> 0 | K18: =I18+J18 -> 0.089046 | L18: =I18*Inputs!$B$17+J18 -> 0.18521568 | M18: E | N18: Measured $0.089: the most expensive single call. Cache it per skill.
A19: A15 | B19: Career paths | C19: Each generation | D19: mini | E19: 2500 | F19: 2500 | G19: 0 | H19: 0 | I19: =IFERROR((E19*INDEX(Inputs!$B$4:$B$6,MATCH(D19,Inputs!$A$4:$A$6,0))+F19*INDEX(Inputs!$C$4:$C$6,MATCH(D19,Inputs!$A$4:$A$6,0)))/1000000,0) -> 0.013125 | J19: =G19/60*Inputs!$B$9+H19/1000000*Inputs!$B$10 -> 0 | K19: =I19+J19 -> 0.013125 | L19: =I19*Inputs!$B$17+J19 -> 0.0273 | M19: C
A20: A16 | B20: Performance review AI assist | C20: Per employee per review cycle (3 calls) | D20: sonnet | E20: 6000 | F20: 1500 | G20: 0 | H20: 0 | I20: =IFERROR((E20*INDEX(Inputs!$B$4:$B$6,MATCH(D20,Inputs!$A$4:$A$6,0))+F20*INDEX(Inputs!$C$4:$C$6,MATCH(D20,Inputs!$A$4:$A$6,0)))/1000000,0) -> 0.0405 | J20: =G20/60*Inputs!$B$9+H20/1000000*Inputs!$B$10 -> 0 | K20: =I20+J20 -> 0.0405 | L20: =I20*Inputs!$B$17+J20 -> 0.08424 | M20: D | N20: Five call sites; ~3 per employee per cycle.
A21: A17 | B21: Career profile extraction | C21: Once per user (CV upload) | D21: sonnet | E21: 5000 | F21: 1100 | G21: 0 | H21: 0 | I21: =IFERROR((E21*INDEX(Inputs!$B$4:$B$6,MATCH(D21,Inputs!$A$4:$A$6,0))+F21*INDEX(Inputs!$C$4:$C$6,MATCH(D21,Inputs!$A$4:$A$6,0)))/1000000,0) -> 0.0315 | J21: =G21/60*Inputs!$B$9+H21/1000000*Inputs!$B$10 -> 0 | K21: =I21+J21 -> 0.0315 | L21: =I21*Inputs!$B$17+J21 -> 0.06552 | M21: D | N21: One-time.
A22: A18 | B22: Discovery interview synthesis | C22: Once per user | D22: sonnet | E22: 3000 | F22: 600 | G22: 0 | H22: 0 | I22: =IFERROR((E22*INDEX(Inputs!$B$4:$B$6,MATCH(D22,Inputs!$A$4:$A$6,0))+F22*INDEX(Inputs!$C$4:$C$6,MATCH(D22,Inputs!$A$4:$A$6,0)))/1000000,0) -> 0.018 | J22: =G22/60*Inputs!$B$9+H22/1000000*Inputs!$B$10 -> 0 | K22: =I22+J22 -> 0.018 | L22: =I22*Inputs!$B$17+J22 -> 0.03744 | M22: D | N22: One-time.
A23: A19 | B23: Task breakdown | C23: Each breakdown | D23: mini | E23: 600 | F23: 300 | G23: 0 | H23: 0 | I23: =IFERROR((E23*INDEX(Inputs!$B$4:$B$6,MATCH(D23,Inputs!$A$4:$A$6,0))+F23*INDEX(Inputs!$C$4:$C$6,MATCH(D23,Inputs!$A$4:$A$6,0)))/1000000,0) -> 0.0018 | J23: =G23/60*Inputs!$B$9+H23/1000000*Inputs!$B$10 -> 0 | K23: =I23+J23 -> 0.0018 | L23: =I23*Inputs!$B$17+J23 -> 0.003744 | M23: C
A24: H1 | B24: Candidate CV scoring | C24: Each CV scored (HR) | D24: sonnet | E24: 7000 | F24: 2500 | G24: 0 | H24: 0 | I24: =IFERROR((E24*INDEX(Inputs!$B$4:$B$6,MATCH(D24,Inputs!$A$4:$A$6,0))+F24*INDEX(Inputs!$C$4:$C$6,MATCH(D24,Inputs!$A$4:$A$6,0)))/1000000,0) -> 0.0585 | J24: =G24/60*Inputs!$B$9+H24/1000000*Inputs!$B$10 -> 0 | K24: =I24+J24 -> 0.0585 | L24: =I24*Inputs!$B$17+J24 -> 0.12168 | M24: D | N24: HR-initiated.
A25: H2 | B25: Candidate interview assessment | C25: Each assessment (HR) | D25: sonnet | E25: 2500 | F25: 800 | G25: 0 | H25: 0 | I25: =IFERROR((E25*INDEX(Inputs!$B$4:$B$6,MATCH(D25,Inputs!$A$4:$A$6,0))+F25*INDEX(Inputs!$C$4:$C$6,MATCH(D25,Inputs!$A$4:$A$6,0)))/1000000,0) -> 0.0195 | J25: =G25/60*Inputs!$B$9+H25/1000000*Inputs!$B$10 -> 0 | K25: =I25+J25 -> 0.0195 | L25: =I25*Inputs!$B$17+J25 -> 0.04056 | M25: D
A26: H3 | B26: Candidate ranking | C26: Each ranking run (HR) | D26: sonnet | E26: 6000 | F26: 2000 | G26: 0 | H26: 0 | I26: =IFERROR((E26*INDEX(Inputs!$B$4:$B$6,MATCH(D26,Inputs!$A$4:$A$6,0))+F26*INDEX(Inputs!$C$4:$C$6,MATCH(D26,Inputs!$A$4:$A$6,0)))/1000000,0) -> 0.048 | J26: =G26/60*Inputs!$B$9+H26/1000000*Inputs!$B$10 -> 0 | K26: =I26+J26 -> 0.048 | L26: =I26*Inputs!$B$17+J26 -> 0.09984 | M26: D
A27: H4 | B27: Exit-interview analysis | C27: Each exit interview (HR) | D27: sonnet | E27: 3000 | F27: 1200 | G27: 0 | H27: 0 | I27: =IFERROR((E27*INDEX(Inputs!$B$4:$B$6,MATCH(D27,Inputs!$A$4:$A$6,0))+F27*INDEX(Inputs!$C$4:$C$6,MATCH(D27,Inputs!$A$4:$A$6,0)))/1000000,0) -> 0.027 | J27: =G27/60*Inputs!$B$9+H27/1000000*Inputs!$B$10 -> 0 | K27: =I27+J27 -> 0.027 | L27: =I27*Inputs!$B$17+J27 -> 0.05616 | M27: D
A28: H5 | B28: Flight-risk score | C28: Each employee run (HR) | D28: sonnet | E28: 3000 | F28: 600 | G28: 0 | H28: 0 | I28: =IFERROR((E28*INDEX(Inputs!$B$4:$B$6,MATCH(D28,Inputs!$A$4:$A$6,0))+F28*INDEX(Inputs!$C$4:$C$6,MATCH(D28,Inputs!$A$4:$A$6,0)))/1000000,0) -> 0.018 | J28: =G28/60*Inputs!$B$9+H28/1000000*Inputs!$B$10 -> 0 | K28: =I28+J28 -> 0.018 | L28: =I28*Inputs!$B$17+J28 -> 0.03744 | M28: D
A29: H6 | B29: Succession ranking | C29: Each role run (HR) | D29: sonnet | E29: 1837 | F29: 738 | G29: 0 | H29: 0 | I29: =IFERROR((E29*INDEX(Inputs!$B$4:$B$6,MATCH(D29,Inputs!$A$4:$A$6,0))+F29*INDEX(Inputs!$C$4:$C$6,MATCH(D29,Inputs!$A$4:$A$6,0)))/1000000,0) -> 0.016581 | J29: =G29/60*Inputs!$B$9+H29/1000000*Inputs!$B$10 -> 0 | K29: =I29+J29 -> 0.016581 | L29: =I29*Inputs!$B$17+J29 -> 0.03448848 | M29: D | N29: Measured.
A30: H7 | B30: Job description generation | C30: Each JD (HR) | D30: mini | E30: 1200 | F30: 900 | G30: 0 | H30: 0 | I30: =IFERROR((E30*INDEX(Inputs!$B$4:$B$6,MATCH(D30,Inputs!$A$4:$A$6,0))+F30*INDEX(Inputs!$C$4:$C$6,MATCH(D30,Inputs!$A$4:$A$6,0)))/1000000,0) -> 0.00495 | J30: =G30/60*Inputs!$B$9+H30/1000000*Inputs!$B$10 -> 0 | K30: =I30+J30 -> 0.00495 | L30: =I30*Inputs!$B$17+J30 -> 0.010296 | M30: C
A31: H8 | B31: Interview question set | C31: Each set (HR) | D31: mini | E31: 1200 | F31: 1000 | G31: 0 | H31: 0 | I31: =IFERROR((E31*INDEX(Inputs!$B$4:$B$6,MATCH(D31,Inputs!$A$4:$A$6,0))+F31*INDEX(Inputs!$C$4:$C$6,MATCH(D31,Inputs!$A$4:$A$6,0)))/1000000,0) -> 0.0054 | J31: =G31/60*Inputs!$B$9+H31/1000000*Inputs!$B$10 -> 0 | K31: =I31+J31 -> 0.0054 | L31: =I31*Inputs!$B$17+J31 -> 0.011232 | M31: C
A32: H9 | B32: Survey question drafting | C32: Each draft (HR) | D32: mini | E32: 800 | F32: 1000 | G32: 0 | H32: 0 | I32: =IFERROR((E32*INDEX(Inputs!$B$4:$B$6,MATCH(D32,Inputs!$A$4:$A$6,0))+F32*INDEX(Inputs!$C$4:$C$6,MATCH(D32,Inputs!$A$4:$A$6,0)))/1000000,0) -> 0.0051 | J32: =G32/60*Inputs!$B$9+H32/1000000*Inputs!$B$10 -> 0 | K32: =I32+J32 -> 0.0051 | L32: =I32*Inputs!$B$17+J32 -> 0.010608 | M32: C
A33: H10 | B33: Role grading suggestion | C33: Each suggestion (HR) | D33: mini | E33: 1200 | F33: 800 | G33: 0 | H33: 0 | I33: =IFERROR((E33*INDEX(Inputs!$B$4:$B$6,MATCH(D33,Inputs!$A$4:$A$6,0))+F33*INDEX(Inputs!$C$4:$C$6,MATCH(D33,Inputs!$A$4:$A$6,0)))/1000000,0) -> 0.0045 | J33: =G33/60*Inputs!$B$9+H33/1000000*Inputs!$B$10 -> 0 | K33: =I33+J33 -> 0.0045 | L33: =I33*Inputs!$B$17+J33 -> 0.00936 | M33: C
A35: Cost class: C = AI-light (Haiku / GPT-5.4 Mini); D = AI-standard (Sonnet); E = heavy (voice or web search). Class A and B features have no per-use AI cost; see the Features sheet.

Sheet Usage
A1: AI cost per seat per month, by usage profile
A2: Units are what one employee does in a month (HR-initiated rows are per 100 seats). Edit the blue cells to match what you expect clients to do.
A4: ID | B4: Feature | C4: Unit | D4: Per | E4: Light | F4: Typical | G4: Heavy | H4: Cost/use EN | I4: Cost/use AR | J4: Light EN | K4: Typical EN | L4: Heavy EN | M4: Light AR | N4: Typical AR | O4: Heavy AR
A5: A1 | B5: =AI_Costs!B5 -> Daily insight | C5: days opened per month | D5: 1 | E5: 6 | F5: 14 | G5: 22 | H5: =AI_Costs!K5 -> 0.0072 | I5: =AI_Costs!L5 -> 0.014976 | J5: =E5*H5/$D5 -> 0.0432 | K5: =F5*H5/$D5 -> 0.1008 | L5: =G5*H5/$D5 -> 0.1584 | M5: =E5*I5/$D5 -> 0.089856 | N5: =F5*I5/$D5 -> 0.209664 | O5: =G5*I5/$D5 -> 0.329472
A6: A2 | B6: =AI_Costs!B6 -> Coach reply | C6: Coach messages | D6: 1 | E6: 3 | F6: 20 | G6: 80 | H6: =AI_Costs!K6 -> 0.0027 | I6: =AI_Costs!L6 -> 0.005616 | J6: =E6*H6/$D6 -> 0.0081 | K6: =F6*H6/$D6 -> 0.054 | L6: =G6*H6/$D6 -> 0.216 | M6: =E6*I6/$D6 -> 0.016848 | N6: =F6*I6/$D6 -> 0.11232 | O6: =G6*I6/$D6 -> 0.44928
A7: A3 | B7: =AI_Costs!B7 -> Coach memory update | C7: Coach messages (memory update) | D7: 1 | E7: =E6 -> 3 | F7: =F6 -> 20 | G7: =G6 -> 80 | H7: =AI_Costs!K7 -> 0.00265 | I7: =AI_Costs!L7 -> 0.005512 | J7: =E7*H7/$D7 -> 0.00795 | K7: =F7*H7/$D7 -> 0.053 | L7: =G7*H7/$D7 -> 0.212 | M7: =E7*I7/$D7 -> 0.016536 | N7: =F7*I7/$D7 -> 0.11024 | O7: =G7*I7/$D7 -> 0.44096
A8: A4 | B8: =AI_Costs!B8 -> Coach session summary | C8: Coach sessions | D8: 1 | E8: =E6/8 -> 0.375 | F8: =F6/8 -> 2.5 | G8: =G6/8 -> 10 | H8: =AI_Costs!K8 -> 0.007 | I8: =AI_Costs!L8 -> 0.01456 | J8: =E8*H8/$D8 -> 0.002625 | K8: =F8*H8/$D8 -> 0.0175 | L8: =G8*H8/$D8 -> 0.07 | M8: =E8*I8/$D8 -> 0.00546 | N8: =F8*I8/$D8 -> 0.0364 | O8: =G8*I8/$D8 -> 0.1456
A9: A5 | B9: =AI_Costs!B9 -> Role-play turn (text) | C9: role-play turns (text) | D9: 1 | E9: 1 | F9: 10 | G9: 30 | H9: =AI_Costs!K9 -> 0.0033 | I9: =AI_Costs!L9 -> 0.006864 | J9: =E9*H9/$D9 -> 0.0033 | K9: =F9*H9/$D9 -> 0.033 | L9: =G9*H9/$D9 -> 0.099 | M9: =E9*I9/$D9 -> 0.006864 | N9: =F9*I9/$D9 -> 0.06864 | O9: =G9*I9/$D9 -> 0.20592
A10: A6 | B10: =AI_Costs!B10 -> Voice role-play session (speech only) | C10: voice role-play sessions | D10: 1 | E10: 0 | F10: 0.1 | G10: 0.5 | H10: =AI_Costs!K10 -> 0.26266667 | I10: =AI_Costs!L10 -> 0.26266667 | J10: =E10*H10/$D10 -> 0 | K10: =F10*H10/$D10 -> 0.026266667 | L10: =G10*H10/$D10 -> 0.13133333 | M10: =E10*I10/$D10 -> 0 | N10: =F10*I10/$D10 -> 0.026266667 | O10: =G10*I10/$D10 -> 0.13133333
A11: A7 | B11: =AI_Costs!B11 -> Coach voice exchange (speech only) | C11: spoken Coach exchanges | D11: 1 | E11: 0 | F11: 0 | G11: 5 | H11: =AI_Costs!K11 -> 0.017933333 | I11: =AI_Costs!L11 -> 0.017933333 | J11: =E11*H11/$D11 -> 0 | K11: =F11*H11/$D11 -> 0 | L11: =G11*H11/$D11 -> 0.089666667 | M11: =E11*I11/$D11 -> 0 | N11: =F11*I11/$D11 -> 0 | O11: =G11*I11/$D11 -> 0.089666667
A12: A8 | B12: =AI_Costs!B12 -> Gap analysis: competency extraction | C12: gap analyses | D12: 1 | E12: 0.05 | F12: 0.25 | G12: 1 | H12: =AI_Costs!K12 -> 0.0585 | I12: =AI_Costs!L12 -> 0.12168 | J12: =E12*H12/$D12 -> 0.002925 | K12: =F12*H12/$D12 -> 0.014625 | L12: =G12*H12/$D12 -> 0.0585 | M12: =E12*I12/$D12 -> 0.006084 | N12: =F12*I12/$D12 -> 0.03042 | O12: =G12*I12/$D12 -> 0.12168
A13: A9 | B13: =AI_Costs!B13 -> Gap analysis: role-context inference | C13: gap analyses (role context) | D13: 1 | E13: =E12 -> 0.05 | F13: =F12 -> 0.25 | G13: =G12 -> 1 | H13: =AI_Costs!K13 -> 0.018 | I13: =AI_Costs!L13 -> 0.03744 | J13: =E13*H13/$D13 -> 0.0009 | K13: =F13*H13/$D13 -> 0.0045 | L13: =G13*H13/$D13 -> 0.018 | M13: =E13*I13/$D13 -> 0.001872 | N13: =F13*I13/$D13 -> 0.00936 | O13: =G13*I13/$D13 -> 0.03744
A14: A10 | B14: =AI_Costs!B14 -> Resume Intelligence | C14: CV audits | D14: 1 | E14: 0.05 | F14: 0.15 | G14: 0.5 | H14: =AI_Costs!K14 -> 0.0555 | I14: =AI_Costs!L14 -> 0.11544 | J14: =E14*H14/$D14 -> 0.002775 | K14: =F14*H14/$D14 -> 0.008325 | L14: =G14*H14/$D14 -> 0.02775 | M14: =E14*I14/$D14 -> 0.005772 | N14: =F14*I14/$D14 -> 0.017316 | O14: =G14*I14/$D14 -> 0.05772
A15: A11 | B15: =AI_Costs!B15 -> Career GPS what-if | C15: what-if runs | D15: 1 | E15: 0.1 | F15: 0.5 | G15: 2 | H15: =AI_Costs!K15 -> 0.015 | I15: =AI_Costs!L15 -> 0.0312 | J15: =E15*H15/$D15 -> 0.0015 | K15: =F15*H15/$D15 -> 0.0075 | L15: =G15*H15/$D15 -> 0.03 | M15: =E15*I15/$D15 -> 0.00312 | N15: =F15*I15/$D15 -> 0.0156 | O15: =G15*I15/$D15 -> 0.0624
A16: A12 | B16: =AI_Costs!B16 -> Notes analysis | C16: notes analysed | D16: 1 | E16: 0.3 | F16: 1.5 | G16: 4 | H16: =AI_Costs!K16 -> 0.0135 | I16: =AI_Costs!L16 -> 0.02808 | J16: =E16*H16/$D16 -> 0.00405 | K16: =F16*H16/$D16 -> 0.02025 | L16: =G16*H16/$D16 -> 0.054 | M16: =E16*I16/$D16 -> 0.008424 | N16: =F16*I16/$D16 -> 0.04212 | O16: =G16*I16/$D16 -> 0.11232
A17: A13 | B17: =AI_Costs!B17 -> Case-study scoring | C17: case studies scored | D17: 1 | E17: 0.05 | F17: 0.2 | G17: 0.5 | H17: =AI_Costs!K17 -> 0.0165 | I17: =AI_Costs!L17 -> 0.03432 | J17: =E17*H17/$D17 -> 0.000825 | K17: =F17*H17/$D17 -> 0.0033 | L17: =G17*H17/$D17 -> 0.00825 | M17: =E17*I17/$D17 -> 0.001716 | N17: =F17*I17/$D17 -> 0.006864 | O17: =G17*I17/$D17 -> 0.01716
A18: A14 | B18: =AI_Costs!B18 -> Course recommendations (web search) | C18: course recommendation requests | D18: 1 | E18: 0 | F18: 0.2 | G18: 0.6 | H18: =AI_Costs!K18 -> 0.089046 | I18: =AI_Costs!L18 -> 0.18521568 | J18: =E18*H18/$D18 -> 0 | K18: =F18*H18/$D18 -> 0.0178092 | L18: =G18*H18/$D18 -> 0.0534276 | M18: =E18*I18/$D18 -> 0 | N18: =F18*I18/$D18 -> 0.037043136 | O18: =G18*I18/$D18 -> 0.11112941
A19: A15 | B19: =AI_Costs!B19 -> Career paths | C19: career path generations | D19: 1 | E19: 0.02 | F19: 0.1 | G19: 0.3 | H19: =AI_Costs!K19 -> 0.013125 | I19: =AI_Costs!L19 -> 0.0273 | J19: =E19*H19/$D19 -> 0.0002625 | K19: =F19*H19/$D19 -> 0.0013125 | L19: =G19*H19/$D19 -> 0.0039375 | M19: =E19*I19/$D19 -> 0.000546 | N19: =F19*I19/$D19 -> 0.00273 | O19: =G19*I19/$D19 -> 0.00819
A20: A16 | B20: =AI_Costs!B20 -> Performance review AI assist | C20: review cycles per month | D20: 1 | E20: 0.15 | F20: 0.33 | G20: 0.5 | H20: =AI_Costs!K20 -> 0.0405 | I20: =AI_Costs!L20 -> 0.08424 | J20: =E20*H20/$D20 -> 0.006075 | K20: =F20*H20/$D20 -> 0.013365 | L20: =G20*H20/$D20 -> 0.02025 | M20: =E20*I20/$D20 -> 0.012636 | N20: =F20*I20/$D20 -> 0.0277992 | O20: =G20*I20/$D20 -> 0.04212
A21: A17 | B21: =AI_Costs!B21 -> Career profile extraction | C21: profile extractions (amortised) | D21: 1 | E21: 0.02 | F21: 0.03 | G21: 0.05 | H21: =AI_Costs!K21 -> 0.0315 | I21: =AI_Costs!L21 -> 0.06552 | J21: =E21*H21/$D21 -> 0.00063 | K21: =F21*H21/$D21 -> 0.000945 | L21: =G21*H21/$D21 -> 0.001575 | M21: =E21*I21/$D21 -> 0.0013104 | N21: =F21*I21/$D21 -> 0.0019656 | O21: =G21*I21/$D21 -> 0.003276
A22: A18 | B22: =AI_Costs!B22 -> Discovery interview synthesis | C22: discovery syntheses (amortised) | D22: 1 | E22: 0.02 | F22: 0.03 | G22: 0.05 | H22: =AI_Costs!K22 -> 0.018 | I22: =AI_Costs!L22 -> 0.03744 | J22: =E22*H22/$D22 -> 0.00036 | K22: =F22*H22/$D22 -> 0.00054 | L22: =G22*H22/$D22 -> 0.0009 | M22: =E22*I22/$D22 -> 0.0007488 | N22: =F22*I22/$D22 -> 0.0011232 | O22: =G22*I22/$D22 -> 0.001872
A23: A19 | B23: =AI_Costs!B23 -> Task breakdown | C23: task breakdowns | D23: 1 | E23: 1 | F23: 4 | G23: 10 | H23: =AI_Costs!K23 -> 0.0018 | I23: =AI_Costs!L23 -> 0.003744 | J23: =E23*H23/$D23 -> 0.0018 | K23: =F23*H23/$D23 -> 0.0072 | L23: =G23*H23/$D23 -> 0.018 | M23: =E23*I23/$D23 -> 0.003744 | N23: =F23*I23/$D23 -> 0.014976 | O23: =G23*I23/$D23 -> 0.03744
A24: H1 | B24: =AI_Costs!B24 -> Candidate CV scoring | C24: CVs scored per 100 seats | D24: 100 | E24: 40 | F24: 40 | G24: 40 | H24: =AI_Costs!K24 -> 0.0585 | I24: =AI_Costs!L24 -> 0.12168 | J24: =E24*H24/$D24 -> 0.0234 | K24: =F24*H24/$D24 -> 0.0234 | L24: =G24*H24/$D24 -> 0.0234 | M24: =E24*I24/$D24 -> 0.048672 | N24: =F24*I24/$D24 -> 0.048672 | O24: =G24*I24/$D24 -> 0.048672
A25: H2 | B25: =AI_Costs!B25 -> Candidate interview assessment | C25: assessments per 100 seats | D25: 100 | E25: 12 | F25: 12 | G25: 12 | H25: =AI_Costs!K25 -> 0.0195 | I25: =AI_Costs!L25 -> 0.04056 | J25: =E25*H25/$D25 -> 0.00234 | K25: =F25*H25/$D25 -> 0.00234 | L25: =G25*H25/$D25 -> 0.00234 | M25: =E25*I25/$D25 -> 0.0048672 | N25: =F25*I25/$D25 -> 0.0048672 | O25: =G25*I25/$D25 -> 0.0048672
... A33: H10 | B33: =AI_Costs!B33 -> Role grading suggestion | C33: role gradings per 100 seats | D33: 100 | E33: 2 | F33: 2 | G33: 2 | H33: =AI_Costs!K33 -> 0.0045 | I33: =AI_Costs!L33 -> 0.00936 | J33: =E33*H33/$D33 -> 9e-05 | K33: =F33*H33/$D33 -> 9e-05 | L33: =G33*H33/$D33 -> 9e-05 | M33: =E33*I33/$D33 -> 0.0001872 | N33: =F33*I33/$D33 -> 0.0001872 | O33: =G33*I33/$D33 -> 0.0001872
B35: AI cost per seat per month | J35: =SUM(J5:J33) -> 0.11813493 | K35: =SUM(K5:K33) -> 0.4150958 | L35: =SUM(L5:L33) -> 1.3018475 | M35: =SUM(M5:M33) -> 0.24572065 | N35: =SUM(N5:N33) -> 0.83503126 | O35: =SUM(O5:O33) -> 2.4691629
B36: Blended with the Arabic share set on Inputs | J36: =J35*(1-Inputs!$B$18)+M35*Inputs!$B$18 -> 0.18192779 | K36: =K35*(1-Inputs!$B$18)+N35*Inputs!$B$18 -> 0.62506353 | L36: =L35*(1-Inputs!$B$18)+O35*Inputs!$B$18 -> 1.8855052
B38: How to read: columns J-L are English, M-O are Arabic. The blended row (J-L) is what the Pricing sheet uses.

Sheet Features
A1: Every platform feature, by what it costs to run
A2: Class A = free to run (database only). B = storage / bandwidth. C = AI-light. D = AI-standard (Sonnet). E = heavy (voice / web search). The bundle column is the proposed feature-based packaging.
A4: Module | B4: What it does | C4: Cost class | D4: Cost driver | E4: Proposed bundle | F4: Approx. cost per seat per month
A5: Employee directory and records | B5: People, titles, departments, managers, status, seat management | C5: A | D5: Database rows | E5: Core HR | F5: ~$0
A6: Employee file and documents | B6: Required and custom document types, custom fields, status/manager/department history, insurance | C6: A+B | D6: Rows + file storage | E6: Core HR | F6: ~$0.01
A7: Org chart and planning | B7: Reporting lines, vacant/future positions, snapshots, saved views | C7: A | D7: Database rows | E7: Core HR | F7: ~$0
A8: Job architecture | B8: Families, roles, grades, competency requirements (manual) | C8: A | D8: Database rows | E8: Core HR | F8: ~$0
A9: Competency framework | B9: Company's own competencies mapped to 8 dimensions (manual) | C9: A | D9: Database rows | E9: Core HR | F9: ~$0
A10: Leave management | B10: Types, balances, requests, approvals, working-day calendars and holidays | C10: A | D10: Database rows | E10: Core HR | F10: ~$0
A11: Attendance | B11: Check-in/out in the company's timezone, import, reports | C11: A | D11: Database rows | E11: Core HR | F11: ~$0
A12: HR letters and requests | B12: Employee requests and HR-issued letters | C12: A | D12: Database rows | E12: Core HR | F12: ~$0
A13: Compensation | B13: Salary records, bands, proposals, approvals, full audit log | C13: A | D13: Database rows | E13: Core HR | F13: ~$0
A14: Hiring pipeline (manual) | B14: Postings, candidates, stages, notes, history, invite-to-join | C14: A+B | D14: Rows + CV storage | E14: Core HR | F14: ~$0.01
A15: Performance reviews and impact cycles | B15: Cycles, steps, escalations, reminders (workflow, no AI) | C15: A | D15: Database rows + email | E15: Core HR | F15: ~$0
... A31: Web-search course recommendations | B31: Live search for real courses | C31: E | D31: Sonnet with ~21k input tokens | E31: Metered pack | F31: $0.09 per request

Sheet Pricing
A1: Prices and margins
A2: Gross margin = revenue minus AI, hosting, storage, support and payment costs. Fixed platform cost is shared across ALL paying seats on the platform, so margin rises with scale.
A4: Total paying seats on the platform (all clients) | B4: 250
A5: Complete price ($ per employee per month) | B5: =Inputs!B43 -> 8
A7: Unit economics per seat per month | B7: Light | C7: Typical | D7: Heavy
A8: Revenue | B8: =$B$5 -> 8 | C8: =$B$5 -> 8 | D8: =$B$5 -> 8
A9: AI cost (blended English/Arabic) | B9: =-Usage!J36 -> -0.18192779 | C9: =-Usage!K36 -> -0.62506353 | D9: =-Usage!L36 -> -1.8855052
A10: Storage, bandwidth, email | B10: =-Inputs!$B$32 -> -0.05 | C10: =-Inputs!$B$32 -> -0.05 | D10: =-Inputs!$B$32 -> -0.05
A11: Support and payment costs | B11: =-B8*(Inputs!$B$33+Inputs!$B$34) -> -0.8 | C11: =-C8*(Inputs!$B$33+Inputs!$B$34) -> -0.8 | D11: =-D8*(Inputs!$B$33+Inputs!$B$34) -> -0.8
A12: Fixed platform cost per seat | B12: =-Inputs!$B$29/$B$4 -> -0.432 | C12: =-Inputs!$B$29/$B$4 -> -0.432 | D12: =-Inputs!$B$29/$B$4 -> -0.432
A13: Gross profit | B13: =SUM(B8:B12) -> 6.5360722 | C13: =SUM(C8:C12) -> 6.0929365 | D13: =SUM(D8:D12) -> 4.8324948
A14: Gross margin | B14: =IF(B8=0,0,B13/B8) -> 0.81700903 | C14: =IF(C8=0,0,C13/C8) -> 0.76161706 | D14: =IF(D8=0,0,D13/D8) -> 0.60406185
A17: Gross margin: TYPICAL usage (blended language) by platform size and price
A18: Total seats \ price per seat | B18: 4 | C18: 5 | D18: 6 | E18: 7 | F18: 8 | G18: 9
A19: 25 | B19: =1-Inputs!$B$33-Inputs!$B$34-(Usage!$K$36+Inputs!$B$32+Inputs!$B$29/$A19)/B$18 -> -0.34876588 | C19: =1-Inputs!$B$33-Inputs!$B$34-(Usage!$K$36+Inputs!$B$32+Inputs!$B$29/$A19)/C$18 -> -0.099012705 | D19: =1-Inputs!$B$33-Inputs!$B$34-(Usage!$K$36+Inputs!$B$32+Inputs!$B$29/$A19)/D$18 -> 0.067489412 | E19: =1-Inputs!$B$33-Inputs!$B$34-(Usage!$K$36+Inputs!$B$32+Inputs!$B$29/$A19)/E$18 -> 0.1864195 | F19: =1-Inputs!$B$33-Inputs!$B$34-(Usage!$K$36+Inputs!$B$32+Inputs!$B$29/$A19)/F$18 -> 0.27561706 | G19: =1-Inputs!$B$33-Inputs!$B$34-(Usage!$K$36+Inputs!$B$32+Inputs!$B$29/$A19)/G$18 -> 0.34499294
A20: 50 | B20: =1-Inputs!$B$33-Inputs!$B$34-(Usage!$K$36+Inputs!$B$32+Inputs!$B$29/$A20)/B$18 -> 0.19123412 | C20: =1-Inputs!$B$33-Inputs!$B$34-(Usage!$K$36+Inputs!$B$32+Inputs!$B$29/$A20)/C$18 -> 0.33298729 | D20: =1-Inputs!$B$33-Inputs!$B$34-(Usage!$K$36+Inputs!$B$32+Inputs!$B$29/$A20)/D$18 -> 0.42748941 | E20: =1-Inputs!$B$33-Inputs!$B$34-(Usage!$K$36+Inputs!$B$32+Inputs!$B$29/$A20)/E$18 -> 0.49499092 | F20: =1-Inputs!$B$33-Inputs!$B$34-(Usage!$K$36+Inputs!$B$32+Inputs!$B$29/$A20)/F$18 -> 0.54561706 | G20: =1-Inputs!$B$33-Inputs!$B$34-(Usage!$K$36+Inputs!$B$32+Inputs!$B$29/$A20)/G$18 -> 0.58499294
A21: 100 | B21: =1-Inputs!$B$33-Inputs!$B$34-(Usage!$K$36+Inputs!$B$32+Inputs!$B$29/$A21)/B$18 -> 0.46123412 | C21: =1-Inputs!$B$33-Inputs!$B$34-(Usage!$K$36+Inputs!$B$32+Inputs!$B$29/$A21)/C$18 -> 0.54898729 | D21: =1-Inputs!$B$33-Inputs!$B$34-(Usage!$K$36+Inputs!$B$32+Inputs!$B$29/$A21)/D$18 -> 0.60748941 | E21: =1-Inputs!$B$33-Inputs!$B$34-(Usage!$K$36+Inputs!$B$32+Inputs!$B$29/$A21)/E$18 -> 0.64927664 | F21: =1-Inputs!$B$33-Inputs!$B$34-(Usage!$K$36+Inputs!$B$32+Inputs!$B$29/$A21)/F$18 -> 0.68061706 | G21: =1-Inputs!$B$33-Inputs!$B$34-(Usage!$K$36+Inputs!$B$32+Inputs!$B$29/$A21)/G$18 -> 0.70499294
A22: 250 | B22: =1-Inputs!$B$33-Inputs!$B$34-(Usage!$K$36+Inputs!$B$32+Inputs!$B$29/$A22)/B$18 -> 0.62323412 | C22: =1-Inputs!$B$33-Inputs!$B$34-(Usage!$K$36+Inputs!$B$32+Inputs!$B$29/$A22)/C$18 -> 0.67858729 | D22: =1-Inputs!$B$33-Inputs!$B$34-(Usage!$K$36+Inputs!$B$32+Inputs!$B$29/$A22)/D$18 -> 0.71548941 | E22: =1-Inputs!$B$33-Inputs!$B$34-(Usage!$K$36+Inputs!$B$32+Inputs!$B$29/$A22)/E$18 -> 0.74184807 | F22: =1-Inputs!$B$33-Inputs!$B$34-(Usage!$K$36+Inputs!$B$32+Inputs!$B$29/$A22)/F$18 -> 0.76161706 | G22: =1-Inputs!$B$33-Inputs!$B$34-(Usage!$K$36+Inputs!$B$32+Inputs!$B$29/$A22)/G$18 -> 0.77699294
A23: 500 | B23: =1-Inputs!$B$33-Inputs!$B$34-(Usage!$K$36+Inputs!$B$32+Inputs!$B$29/$A23)/B$18 -> 0.67723412 | C23: =1-Inputs!$B$33-Inputs!$B$34-(Usage!$K$36+Inputs!$B$32+Inputs!$B$29/$A23)/C$18 -> 0.72178729 | D23: =1-Inputs!$B$33-Inputs!$B$34-(Usage!$K$36+Inputs!$B$32+Inputs!$B$29/$A23)/D$18 -> 0.75148941 | E23: =1-Inputs!$B$33-Inputs!$B$34-(Usage!$K$36+Inputs!$B$32+Inputs!$B$29/$A23)/E$18 -> 0.77270521 | F23: =1-Inputs!$B$33-Inputs!$B$34-(Usage!$K$36+Inputs!$B$32+Inputs!$B$29/$A23)/F$18 -> 0.78861706 | G23: =1-Inputs!$B$33-Inputs!$B$34-(Usage!$K$36+Inputs!$B$32+Inputs!$B$29/$A23)/G$18 -> 0.80099294
A24: 1000 | B24: =1-Inputs!$B$33-Inputs!$B$34-(Usage!$K$36+Inputs!$B$32+Inputs!$B$29/$A24)/B$18 -> 0.70423412 | C24: =1-Inputs!$B$33-Inputs!$B$34-(Usage!$K$36+Inputs!$B$32+Inputs!$B$29/$A24)/C$18 -> 0.74338729 | D24: =1-Inputs!$B$33-Inputs!$B$34-(Usage!$K$36+Inputs!$B$32+Inputs!$B$29/$A24)/D$18 -> 0.76948941 | E24: =1-Inputs!$B$33-Inputs!$B$34-(Usage!$K$36+Inputs!$B$32+Inputs!$B$29/$A24)/E$18 -> 0.78813378 | F24: =1-Inputs!$B$33-Inputs!$B$34-(Usage!$K$36+Inputs!$B$32+Inputs!$B$29/$A24)/F$18 -> 0.80211706 | G24: =1-Inputs!$B$33-Inputs!$B$34-(Usage!$K$36+Inputs!$B$32+Inputs!$B$29/$A24)/G$18 -> 0.81299294
A25: 2500 | B25: =1-Inputs!$B$33-Inputs!$B$34-(Usage!$K$36+Inputs!$B$32+Inputs!$B$29/$A25)/B$18 -> 0.72043412 | C25: =1-Inputs!$B$33-Inputs!$B$34-(Usage!$K$36+Inputs!$B$32+Inputs!$B$29/$A25)/C$18 -> 0.75634729 | D25: =1-Inputs!$B$33-Inputs!$B$34-(Usage!$K$36+Inputs!$B$32+Inputs!$B$29/$A25)/D$18 -> 0.78028941 | E25: =1-Inputs!$B$33-Inputs!$B$34-(Usage!$K$36+Inputs!$B$32+Inputs!$B$29/$A25)/E$18 -> 0.79739092 | F25: =1-Inputs!$B$33-Inputs!$B$34-(Usage!$K$36+Inputs!$B$32+Inputs!$B$29/$A25)/F$18 -> 0.81021706 | G25: =1-Inputs!$B$33-Inputs!$B$34-(Usage!$K$36+Inputs!$B$32+Inputs!$B$29/$A25)/G$18 -> 0.82019294
A28: Gross margin: HEAVY usage (blended language) by platform size and price
A29: Total seats \ price per seat | B29: 4 | C29: 5 | D29: 6 | E29: 7 | F29: 8 | G29: 9
A30: 25 | B30: =1-Inputs!$B$33-Inputs!$B$34-(Usage!$L$36+Inputs!$B$32+Inputs!$B$29/$A30)/B$29 -> -0.6638763 | C30: =1-Inputs!$B$33-Inputs!$B$34-(Usage!$L$36+Inputs!$B$32+Inputs!$B$29/$A30)/C$29 -> -0.35110104 | D30: =1-Inputs!$B$33-Inputs!$B$34-(Usage!$L$36+Inputs!$B$32+Inputs!$B$29/$A30)/D$29 -> -0.1425842 | E30: =1-Inputs!$B$33-Inputs!$B$34-(Usage!$L$36+Inputs!$B$32+Inputs!$B$29/$A30)/E$29 -> 0.0063564005 | F30: =1-Inputs!$B$33-Inputs!$B$34-(Usage!$L$36+Inputs!$B$32+Inputs!$B$29/$A30)/F$29 -> 0.11806185 | G30: =1-Inputs!$B$33-Inputs!$B$34-(Usage!$L$36+Inputs!$B$32+Inputs!$B$29/$A30)/G$29 -> 0.20494387
A31: 50 | B31: =1-Inputs!$B$33-Inputs!$B$34-(Usage!$L$36+Inputs!$B$32+Inputs!$B$29/$A31)/B$29 -> -0.1238763 | C31: =1-Inputs!$B$33-Inputs!$B$34-(Usage!$L$36+Inputs!$B$32+Inputs!$B$29/$A31)/C$29 -> 0.080898961 | D31: =1-Inputs!$B$33-Inputs!$B$34-(Usage!$L$36+Inputs!$B$32+Inputs!$B$29/$A31)/D$29 -> 0.2174158 | E31: =1-Inputs!$B$33-Inputs!$B$34-(Usage!$L$36+Inputs!$B$32+Inputs!$B$29/$A31)/E$29 -> 0.31492783 | F31: =1-Inputs!$B$33-Inputs!$B$34-(Usage!$L$36+Inputs!$B$32+Inputs!$B$29/$A31)/F$29 -> 0.38806185 | G31: =1-Inputs!$B$33-Inputs!$B$34-(Usage!$L$36+Inputs!$B$32+Inputs!$B$29/$A31)/G$29 -> 0.44494387
A32: 100 | B32: =1-Inputs!$B$33-Inputs!$B$34-(Usage!$L$36+Inputs!$B$32+Inputs!$B$29/$A32)/B$29 -> 0.1461237 | C32: =1-Inputs!$B$33-Inputs!$B$34-(Usage!$L$36+Inputs!$B$32+Inputs!$B$29/$A32)/C$29 -> 0.29689896 | D32: =1-Inputs!$B$33-Inputs!$B$34-(Usage!$L$36+Inputs!$B$32+Inputs!$B$29/$A32)/D$29 -> 0.3974158 | E32: =1-Inputs!$B$33-Inputs!$B$34-(Usage!$L$36+Inputs!$B$32+Inputs!$B$29/$A32)/E$29 -> 0.46921354 | F32: =1-Inputs!$B$33-Inputs!$B$34-(Usage!$L$36+Inputs!$B$32+Inputs!$B$29/$A32)/F$29 -> 0.52306185 | G32: =1-Inputs!$B$33-Inputs!$B$34-(Usage!$L$36+Inputs!$B$32+Inputs!$B$29/$A32)/G$29 -> 0.56494387
A33: 250 | B33: =1-Inputs!$B$33-Inputs!$B$34-(Usage!$L$36+Inputs!$B$32+Inputs!$B$29/$A33)/B$29 -> 0.3081237 | C33: =1-Inputs!$B$33-Inputs!$B$34-(Usage!$L$36+Inputs!$B$32+Inputs!$B$29/$A33)/C$29 -> 0.42649896 | D33: =1-Inputs!$B$33-Inputs!$B$34-(Usage!$L$36+Inputs!$B$32+Inputs!$B$29/$A33)/D$29 -> 0.5054158 | E33: =1-Inputs!$B$33-Inputs!$B$34-(Usage!$L$36+Inputs!$B$32+Inputs!$B$29/$A33)/E$29 -> 0.56178497 | F33: =1-Inputs!$B$33-Inputs!$B$34-(Usage!$L$36+Inputs!$B$32+Inputs!$B$29/$A33)/F$29 -> 0.60406185 | G33: =1-Inputs!$B$33-Inputs!$B$34-(Usage!$L$36+Inputs!$B$32+Inputs!$B$29/$A33)/G$29 -> 0.63694387
A34: 500 | B34: =1-Inputs!$B$33-Inputs!$B$34-(Usage!$L$36+Inputs!$B$32+Inputs!$B$29/$A34)/B$29 -> 0.3621237 | C34: =1-Inputs!$B$33-Inputs!$B$34-(Usage!$L$36+Inputs!$B$32+Inputs!$B$29/$A34)/C$29 -> 0.46969896 | D34: =1-Inputs!$B$33-Inputs!$B$34-(Usage!$L$36+Inputs!$B$32+Inputs!$B$29/$A34)/D$29 -> 0.5414158 | E34: =1-Inputs!$B$33-Inputs!$B$34-(Usage!$L$36+Inputs!$B$32+Inputs!$B$29/$A34)/E$29 -> 0.59264211 | F34: =1-Inputs!$B$33-Inputs!$B$34-(Usage!$L$36+Inputs!$B$32+Inputs!$B$29/$A34)/F$29 -> 0.63106185 | G34: =1-Inputs!$B$33-Inputs!$B$34-(Usage!$L$36+Inputs!$B$32+Inputs!$B$29/$A34)/G$29 -> 0.66094387
A35: 1000 | B35: =1-Inputs!$B$33-Inputs!$B$34-(Usage!$L$36+Inputs!$B$32+Inputs!$B$29/$A35)/B$29 -> 0.3891237 | C35: =1-Inputs!$B$33-Inputs!$B$34-(Usage!$L$36+Inputs!$B$32+Inputs!$B$29/$A35)/C$29 -> 0.49129896 | D35: =1-Inputs!$B$33-Inputs!$B$34-(Usage!$L$36+Inputs!$B$32+Inputs!$B$29/$A35)/D$29 -> 0.5594158 | E35: =1-Inputs!$B$33-Inputs!$B$34-(Usage!$L$36+Inputs!$B$32+Inputs!$B$29/$A35)/E$29 -> 0.60807069 | F35: =1-Inputs!$B$33-Inputs!$B$34-(Usage!$L$36+Inputs!$B$32+Inputs!$B$29/$A35)/F$29 -> 0.64456185 | G35: =1-Inputs!$B$33-Inputs!$B$34-(Usage!$L$36+Inputs!$B$32+Inputs!$B$29/$A35)/G$29 -> 0.67294387
A36: 2500 | B36: =1-Inputs!$B$33-Inputs!$B$34-(Usage!$L$36+Inputs!$B$32+Inputs!$B$29/$A36)/B$29 -> 0.4053237 | C36: =1-Inputs!$B$33-Inputs!$B$34-(Usage!$L$36+Inputs!$B$32+Inputs!$B$29/$A36)/C$29 -> 0.50425896 | D36: =1-Inputs!$B$33-Inputs!$B$34-(Usage!$L$36+Inputs!$B$32+Inputs!$B$29/$A36)/D$29 -> 0.5702158 | E36: =1-Inputs!$B$33-Inputs!$B$34-(Usage!$L$36+Inputs!$B$32+Inputs!$B$29/$A36)/E$29 -> 0.61732783 | F36: =1-Inputs!$B$33-Inputs!$B$34-(Usage!$L$36+Inputs!$B$32+Inputs!$B$29/$A36)/F$29 -> 0.65266185 | G36: =1-Inputs!$B$33-Inputs!$B$34-(Usage!$L$36+Inputs!$B$32+Inputs!$B$29/$A36)/G$29 -> 0.68014387
A39: Lowest price that still hits the margin target (per seat per month)
A40: Total seats | B40: Typical @ low target | C40: Typical @ high target | D40: Heavy @ low target | E40: Heavy @ high target
A41: 25 | B41: =(Usage!$K$36+Inputs!$B$32+Inputs!$B$29/$A41)/(1-Inputs!$B$33-Inputs!$B$34-Inputs!$B$37) -> 33.300424 | C41: =(Usage!$K$36+Inputs!$B$32+Inputs!$B$29/$A41)/(1-Inputs!$B$33-Inputs!$B$34-Inputs!$B$38) -> 49.950635 | D41: =(Usage!$L$36+Inputs!$B$32+Inputs!$B$29/$A41)/(1-Inputs!$B$33-Inputs!$B$34-Inputs!$B$37) -> 41.703368 | E41: =(Usage!$L$36+Inputs!$B$32+Inputs!$B$29/$A41)/(1-Inputs!$B$33-Inputs!$B$34-Inputs!$B$38) -> 62.555052
A42: 50 | B42: =(Usage!$K$36+Inputs!$B$32+Inputs!$B$29/$A42)/(1-Inputs!$B$33-Inputs!$B$34-Inputs!$B$37) -> 18.900424 | C42: =(Usage!$K$36+Inputs!$B$32+Inputs!$B$29/$A42)/(1-Inputs!$B$33-Inputs!$B$34-Inputs!$B$38) -> 28.350635 | D42: =(Usage!$L$36+Inputs!$B$32+Inputs!$B$29/$A42)/(1-Inputs!$B$33-Inputs!$B$34-Inputs!$B$37) -> 27.303368 | E42: =(Usage!$L$36+Inputs!$B$32+Inputs!$B$29/$A42)/(1-Inputs!$B$33-Inputs!$B$34-Inputs!$B$38) -> 40.955052
A43: 100 | B43: =(Usage!$K$36+Inputs!$B$32+Inputs!$B$29/$A43)/(1-Inputs!$B$33-Inputs!$B$34-Inputs!$B$37) -> 11.700424 | C43: =(Usage!$K$36+Inputs!$B$32+Inputs!$B$29/$A43)/(1-Inputs!$B$33-Inputs!$B$34-Inputs!$B$38) -> 17.550635 | D43: =(Usage!$L$36+Inputs!$B$32+Inputs!$B$29/$A43)/(1-Inputs!$B$33-Inputs!$B$34-Inputs!$B$37) -> 20.103368 | E43: =(Usage!$L$36+Inputs!$B$32+Inputs!$B$29/$A43)/(1-Inputs!$B$33-Inputs!$B$34-Inputs!$B$38) -> 30.155052
A44: 250 | B44: =(Usage!$K$36+Inputs!$B$32+Inputs!$B$29/$A44)/(1-Inputs!$B$33-Inputs!$B$34-Inputs!$B$37) -> 7.3804235 | C44: =(Usage!$K$36+Inputs!$B$32+Inputs!$B$29/$A44)/(1-Inputs!$B$33-Inputs!$B$34-Inputs!$B$38) -> 11.070635 | D44: =(Usage!$L$36+Inputs!$B$32+Inputs!$B$29/$A44)/(1-Inputs!$B$33-Inputs!$B$34-Inputs!$B$37) -> 15.783368 | E44: =(Usage!$L$36+Inputs!$B$32+Inputs!$B$29/$A44)/(1-Inputs!$B$33-Inputs!$B$34-Inputs!$B$38) -> 23.675052
A45: 500 | B45: =(Usage!$K$36+Inputs!$B$32+Inputs!$B$29/$A45)/(1-Inputs!$B$33-Inputs!$B$34-Inputs!$B$37) -> 5.9404235 | C45: =(Usage!$K$36+Inputs!$B$32+Inputs!$B$29/$A45)/(1-Inputs!$B$33-Inputs!$B$34-Inputs!$B$38) -> 8.9106353 | D45: =(Usage!$L$36+Inputs!$B$32+Inputs!$B$29/$A45)/(1-Inputs!$B$33-Inputs!$B$34-Inputs!$B$37) -> 14.343368 | E45: =(Usage!$L$36+Inputs!$B$32+Inputs!$B$29/$A45)/(1-Inputs!$B$33-Inputs!$B$34-Inputs!$B$38) -> 21.515052
A46: 1000 | B46: =(Usage!$K$36+Inputs!$B$32+Inputs!$B$29/$A46)/(1-Inputs!$B$33-Inputs!$B$34-Inputs!$B$37) -> 5.2204235 | C46: =(Usage!$K$36+Inputs!$B$32+Inputs!$B$29/$A46)/(1-Inputs!$B$33-Inputs!$B$34-Inputs!$B$38) -> 7.8306353 | D46: =(Usage!$L$36+Inputs!$B$32+Inputs!$B$29/$A46)/(1-Inputs!$B$33-Inputs!$B$34-Inputs!$B$37) -> 13.623368 | E46: =(Usage!$L$36+Inputs!$B$32+Inputs!$B$29/$A46)/(1-Inputs!$B$33-Inputs!$B$34-Inputs!$B$38) -> 20.435052
A47: 2500 | B47: =(Usage!$K$36+Inputs!$B$32+Inputs!$B$29/$A47)/(1-Inputs!$B$33-Inputs!$B$34-Inputs!$B$37) -> 4.7884235 | C47: =(Usage!$K$36+Inputs!$B$32+Inputs!$B$29/$A47)/(1-Inputs!$B$33-Inputs!$B$34-Inputs!$B$38) -> 7.1826353 | D47: =(Usage!$L$36+Inputs!$B$32+Inputs!$B$29/$A47)/(1-Inputs!$B$33-Inputs!$B$34-Inputs!$B$37) -> 13.191368 | E47: =(Usage!$L$36+Inputs!$B$32+Inputs!$B$29/$A47)/(1-Inputs!$B$33-Inputs!$B$34-Inputs!$B$38) -> 19.787052

Sheet Guardrails
A1: Guardrails that protect the margin
A2: The AI credit cap (organizations.monthly_ai_budget_usd) is the enforcement mechanism that already exists. These are the per-seat caps that keep each price at or above the margin target.
A4: AI credit cap per seat per month that still hits the LOW target
A5: Total seats \ price per seat | B5: 4 | C5: 5 | D5: 6 | E5: 7 | F5: 8 | G5: 9
A6: 25 | B6: =MAX(0,B$5*(1-Inputs!$B$33-Inputs!$B$34-Inputs!$B$37)-Inputs!$B$32-Inputs!$B$29/$A6) -> 0 | C6: =MAX(0,C$5*(1-Inputs!$B$33-Inputs!$B$34-Inputs!$B$37)-Inputs!$B$32-Inputs!$B$29/$A6) -> 0 | D6: =MAX(0,D$5*(1-Inputs!$B$33-Inputs!$B$34-Inputs!$B$37)-Inputs!$B$32-Inputs!$B$29/$A6) -> 0 | E6: =MAX(0,E$5*(1-Inputs!$B$33-Inputs!$B$34-Inputs!$B$37)-Inputs!$B$32-Inputs!$B$29/$A6) -> 0 | F6: =MAX(0,F$5*(1-Inputs!$B$33-Inputs!$B$34-Inputs!$B$37)-Inputs!$B$32-Inputs!$B$29/$A6) -> 0 | G6: =MAX(0,G$5*(1-Inputs!$B$33-Inputs!$B$34-Inputs!$B$37)-Inputs!$B$32-Inputs!$B$29/$A6) -> 0
A7: 50 | B7: =MAX(0,B$5*(1-Inputs!$B$33-Inputs!$B$34-Inputs!$B$37)-Inputs!$B$32-Inputs!$B$29/$A7) -> 0 | C7: =MAX(0,C$5*(1-Inputs!$B$33-Inputs!$B$34-Inputs!$B$37)-Inputs!$B$32-Inputs!$B$29/$A7) -> 0 | D7: =MAX(0,D$5*(1-Inputs!$B$33-Inputs!$B$34-Inputs!$B$37)-Inputs!$B$32-Inputs!$B$29/$A7) -> 0 | E7: =MAX(0,E$5*(1-Inputs!$B$33-Inputs!$B$34-Inputs!$B$37)-Inputs!$B$32-Inputs!$B$29/$A7) -> 0 | F7: =MAX(0,F$5*(1-Inputs!$B$33-Inputs!$B$34-Inputs!$B$37)-Inputs!$B$32-Inputs!$B$29/$A7) -> 0 | G7: =MAX(0,G$5*(1-Inputs!$B$33-Inputs!$B$34-Inputs!$B$37)-Inputs!$B$32-Inputs!$B$29/$A7) -> 0
A8: 100 | B8: =MAX(0,B$5*(1-Inputs!$B$33-Inputs!$B$34-Inputs!$B$37)-Inputs!$B$32-Inputs!$B$29/$A8) -> 0 | C8: =MAX(0,C$5*(1-Inputs!$B$33-Inputs!$B$34-Inputs!$B$37)-Inputs!$B$32-Inputs!$B$29/$A8) -> 0 | D8: =MAX(0,D$5*(1-Inputs!$B$33-Inputs!$B$34-Inputs!$B$37)-Inputs!$B$32-Inputs!$B$29/$A8) -> 0 | E8: =MAX(0,E$5*(1-Inputs!$B$33-Inputs!$B$34-Inputs!$B$37)-Inputs!$B$32-Inputs!$B$29/$A8) -> 0 | F8: =MAX(0,F$5*(1-Inputs!$B$33-Inputs!$B$34-Inputs!$B$37)-Inputs!$B$32-Inputs!$B$29/$A8) -> 0.07 | G8: =MAX(0,G$5*(1-Inputs!$B$33-Inputs!$B$34-Inputs!$B$37)-Inputs!$B$32-Inputs!$B$29/$A8) -> 0.22
A9: 250 | B9: =MAX(0,B$5*(1-Inputs!$B$33-Inputs!$B$34-Inputs!$B$37)-Inputs!$B$32-Inputs!$B$29/$A9) -> 0.118 | C9: =MAX(0,C$5*(1-Inputs!$B$33-Inputs!$B$34-Inputs!$B$37)-Inputs!$B$32-Inputs!$B$29/$A9) -> 0.268 | D9: =MAX(0,D$5*(1-Inputs!$B$33-Inputs!$B$34-Inputs!$B$37)-Inputs!$B$32-Inputs!$B$29/$A9) -> 0.418 | E9: =MAX(0,E$5*(1-Inputs!$B$33-Inputs!$B$34-Inputs!$B$37)-Inputs!$B$32-Inputs!$B$29/$A9) -> 0.568 | F9: =MAX(0,F$5*(1-Inputs!$B$33-Inputs!$B$34-Inputs!$B$37)-Inputs!$B$32-Inputs!$B$29/$A9) -> 0.718 | G9: =MAX(0,G$5*(1-Inputs!$B$33-Inputs!$B$34-Inputs!$B$37)-Inputs!$B$32-Inputs!$B$29/$A9) -> 0.868
A10: 500 | B10: =MAX(0,B$5*(1-Inputs!$B$33-Inputs!$B$34-Inputs!$B$37)-Inputs!$B$32-Inputs!$B$29/$A10) -> 0.334 | C10: =MAX(0,C$5*(1-Inputs!$B$33-Inputs!$B$34-Inputs!$B$37)-Inputs!$B$32-Inputs!$B$29/$A10) -> 0.484 | D10: =MAX(0,D$5*(1-Inputs!$B$33-Inputs!$B$34-Inputs!$B$37)-Inputs!$B$32-Inputs!$B$29/$A10) -> 0.634 | E10: =MAX(0,E$5*(1-Inputs!$B$33-Inputs!$B$34-Inputs!$B$37)-Inputs!$B$32-Inputs!$B$29/$A10) -> 0.784 | F10: =MAX(0,F$5*(1-Inputs!$B$33-Inputs!$B$34-Inputs!$B$37)-Inputs!$B$32-Inputs!$B$29/$A10) -> 0.934 | G10: =MAX(0,G$5*(1-Inputs!$B$33-Inputs!$B$34-Inputs!$B$37)-Inputs!$B$32-Inputs!$B$29/$A10) -> 1.084
A11: 1000 | B11: =MAX(0,B$5*(1-Inputs!$B$33-Inputs!$B$34-Inputs!$B$37)-Inputs!$B$32-Inputs!$B$29/$A11) -> 0.442 | C11: =MAX(0,C$5*(1-Inputs!$B$33-Inputs!$B$34-Inputs!$B$37)-Inputs!$B$32-Inputs!$B$29/$A11) -> 0.592 | D11: =MAX(0,D$5*(1-Inputs!$B$33-Inputs!$B$34-Inputs!$B$37)-Inputs!$B$32-Inputs!$B$29/$A11) -> 0.742 | E11: =MAX(0,E$5*(1-Inputs!$B$33-Inputs!$B$34-Inputs!$B$37)-Inputs!$B$32-Inputs!$B$29/$A11) -> 0.892 | F11: =MAX(0,F$5*(1-Inputs!$B$33-Inputs!$B$34-Inputs!$B$37)-Inputs!$B$32-Inputs!$B$29/$A11) -> 1.042 | G11: =MAX(0,G$5*(1-Inputs!$B$33-Inputs!$B$34-Inputs!$B$37)-Inputs!$B$32-Inputs!$B$29/$A11) -> 1.192
A12: 2500 | B12: =MAX(0,B$5*(1-Inputs!$B$33-Inputs!$B$34-Inputs!$B$37)-Inputs!$B$32-Inputs!$B$29/$A12) -> 0.5068 | C12: =MAX(0,C$5*(1-Inputs!$B$33-Inputs!$B$34-Inputs!$B$37)-Inputs!$B$32-Inputs!$B$29/$A12) -> 0.6568 | D12: =MAX(0,D$5*(1-Inputs!$B$33-Inputs!$B$34-Inputs!$B$37)-Inputs!$B$32-Inputs!$B$29/$A12) -> 0.8068 | E12: =MAX(0,E$5*(1-Inputs!$B$33-Inputs!$B$34-Inputs!$B$37)-Inputs!$B$32-Inputs!$B$29/$A12) -> 0.9568 | F12: =MAX(0,F$5*(1-Inputs!$B$33-Inputs!$B$34-Inputs!$B$37)-Inputs!$B$32-Inputs!$B$29/$A12) -> 1.1068 | G12: =MAX(0,G$5*(1-Inputs!$B$33-Inputs!$B$34-Inputs!$B$37)-Inputs!$B$32-Inputs!$B$29/$A12) -> 1.2568
A13: Read: at 250 platform seats and a $7 price, AI spend per seat must stay under the figure shown or margin falls below the low target. Set the org's budget to seats x this number.
A15: Product changes that cut AI cost (TYPICAL usage, English)
A16: Change | B16: Saving per seat per month | C16: How
A17: Daily insight on Haiku instead of Sonnet | B17: =Usage!F5*(AI_Costs!K5-(AI_Costs!E5*Inputs!B5+AI_Costs!F5*Inputs!C5)/1000000) -> 0.0672 | C17: One-line change in lib/careerGps/dailyInsight.ts. The output is ~120 tokens of friendly text.
A18: Coach memory updated every 5th message, not every message | B18: =Usage!F7*AI_Costs!K7*(1-1/5) -> 0.0424 | C18: Update the running summary at session end or every 5 exchanges. Removes about a third of Coach cost.
A19: Cache course recommendations per skill (shared) | B19: =Usage!F18*AI_Costs!K18*0.8 -> 0.01424736 | C19: Same skill + level gives the same answer; cache for 30 days across the company, assume an 80% hit rate.
A20: Total saving per seat per month | B20: =SUM(B17:B19) -> 0.12384736
A21: ...as a share of typical AI cost (English) | B21: =IF(Usage!K35=0,0,B20/Usage!K35) -> 0.2983585
A22: Typical blended AI cost per seat after the changes | B22: =Usage!K36-B20*((1-Inputs!B18)+Inputs!B18*Inputs!B17) -> 0.43433859
A23: Typical gross margin at the Pricing sheet's price and size, after the changes | B23: =1-Inputs!B33-Inputs!B34-(B22+Inputs!B32+Inputs!B29/Pricing!B4)/Pricing!B5 -> 0.78545768
